[
		{
			"inputs": [],
			"stateMutability": "nonpayable",
			"type": "constructor"
		},
		{
			"inputs": [
				{
					"internalType": "address",
					"name": "send_token",
					"type": "address"
				},
				{
					"internalType": "address",
					"name": "get_token",
					"type": "address"
				},
				{
					"internalType": "uint256",
					"name": "send_token_amount",
					"type": "uint256"
				},
				{
					"internalType": "uint256",
					"name": "get_token_amount",
					"type": "uint256"
				}
			],
			"name": "swap",
			"outputs": [],
			"stateMutability": "nonpayable",
			"type": "function"
		}
	]
